batch_iter/__init__.py
batch_iter/group_batch_iter.py
batch_iter/simple_batch_iter.py
batch_iter-0.1.1.dist-info/LICENSE
batch_iter-0.1.1.dist-info/METADATA
batch_iter-0.1.1.dist-info/WHEEL
batch_iter-0.1.1.dist-info/top_level.txt
batch_iter-0.1.1.dist-info/RECORD
