Metadata-Version: 2.2
Name: batch_iter
Version: 0.1.1
Summary: Utilities for efficiently iterating over mini-batches of PyTorch tensors
Author: Alex Shtoff
Author-email: <alex.shtf@gmail.com>
Keywords: python,pytorch
Classifier: Development Status :: 3 - Alpha
Classifier: Intended Audience :: Developers
Classifier: Programming Language :: Python :: 3
License-File: LICENSE
Requires-Dist: torch>=2.1.0
Dynamic: author
Dynamic: author-email
Dynamic: classifier
Dynamic: description
Dynamic: description-content-type
Dynamic: keywords
Dynamic: requires-dist
Dynamic: summary
